[
  {
    "category": "platform",
    "placeholderImgUrl": "https://images-assets.nasa.gov/image/GSFC_20171208_Archive_e002096/GSFC_20171208_Archive_e002096~orig.jpg",
    "placeholderImgAlt": "NASA’s Global Hawk aircraft flying over arid land"
  },
  {
    "category": "deployment",
    "placeholderImgUrl": "https://images-assets.nasa.gov/image/AFRC2016-0292-08/AFRC2016-0292-08~orig.jpg",
    "placeholderImgAlt": "NASA’s Global Hawk aircraft being deployed to Florida from Armstrong Flight Research Center"
  }
]
